sphinx_pynpoint_theme/__init__.py
sphinx_pynpoint_theme/breadcrumbs.html
sphinx_pynpoint_theme/footer.html
sphinx_pynpoint_theme/layout.html
sphinx_pynpoint_theme/search.html
sphinx_pynpoint_theme/searchbox.html
sphinx_pynpoint_theme/theme.conf
sphinx_pynpoint_theme/versions.html
sphinx_pynpoint_theme/static/css/badge_only.css
sphinx_pynpoint_theme/static/css/theme copy.css
sphinx_pynpoint_theme/static/css/theme.css
sphinx_pynpoint_theme/static/font/fontawesome_webfont.eot
sphinx_pynpoint_theme/static/font/fontawesome_webfont.svg
sphinx_pynpoint_theme/static/font/fontawesome_webfont.ttf
sphinx_pynpoint_theme/static/font/fontawesome_webfont.woff
sphinx_pynpoint_theme/static/js/theme.js
sphinx_pynpoint_theme-0.2.1.dist-info/METADATA
sphinx_pynpoint_theme-0.2.1.dist-info/WHEEL
sphinx_pynpoint_theme-0.2.1.dist-info/licenses/LICENSE
sphinx_pynpoint_theme-0.2.1.dist-info/RECORD
