Metadata-Version: 2.3
Name: sphinx-pynpoint-theme
Version: 0.2.1
Summary: ETH cosmology theme for Sphinx
Project-URL: Source, https://cosmo-gitlab.phys.ethz.ch/uweschmitt/sphinx-pynpoint-theme
Author-email: Uwe Schmitt <uwe.schmitt@id.ethz.ch>
License: MIT License
License-File: LICENSE
Classifier: Development Status :: 3 - Alpha
Classifier: Intended Audience :: Developers
Classifier: License :: OSI Approved :: MIT License
Classifier: Operating System :: OS Independent
Classifier: Programming Language :: Python :: 3
Classifier: Topic :: Documentation
Classifier: Topic :: Software Development :: Documentation
Requires-Dist: sphinx
Provides-Extra: dev
Requires-Dist: black; extra == 'dev'
Requires-Dist: build; extra == 'dev'
Requires-Dist: hatchling; extra == 'dev'
Requires-Dist: pre-commit; extra == 'dev'
Requires-Dist: ruff; extra == 'dev'
Requires-Dist: tox; extra == 'dev'
Requires-Dist: twine; extra == 'dev'
Requires-Dist: wheel; extra == 'dev'
